<spellcast>
  <sets>
    <group name="exported">
      <set name="exported">
        <head>Quiahuiz Helm</head>
		<item>Rajas Ring</item>
		<item>Yacuruna Ring</item>
		<item>Inanna</item>
		<item></item>
		<item></item>
		<item></item>
		<item></item>
		<item></item>
        <item>Ace of Coins</item>
        <neck>Tlamiztli Collar</neck>
        <sub>Arbuda Grip</sub>
        <body>Twilight Mail</body>
        <left_ring>Beeline Ring</left_ring>
        <neck>Ocachi Gorget</neck>
        <left_ring>Cho'j Band</left_ring>
        <back>Shadow Mantle</back>
        <left_ear>Heartseeker Earring</left_ear>
        <neck>Twilight Torque</neck>
        <neck>Wiglen Gorget</neck>
        <left_ring>Enlivened Ring</left_ring>
        <left_ring>Shadow Ring</left_ring>
        <waist>Zoran's Belt</waist>
        <left_ring>Oneiros Annulet</left_ring>
        <ammo>Bomb Core</ammo>
        <back>Niht Mantle</back>
        <sub>Tzacab Grip</sub>
        <hands>Miki. Gauntlets</hands>
        <back>Engulfer Cape</back>
        <head>Xaddi Headgear</head>
        <item>Kohlrouladen +1</item>
        <left_ear>Merman's Earring</left_ear>
        <main>Cronus</main>
        <item>Airlixir +1</item>
        <neck>Bull Necklace</neck>
        <item>Shining Cloth</item>
        <head>Otomi Helm</head>
        <waist>Flume Belt</waist>
        <item>Airlixir</item>
        <feet>Kar. Sollerets +1</feet>
        <hands>Umuthi Gloves</hands>
        <sub>Rose Strap</sub>
        <feet>Whirlpool Greaves</feet>
        <item>Pearlsack</item>
        <waist>Goading Belt</waist>
        <item>T. Tama-hagane</item>
        <legs>Dux Cuisses</legs>
        <legs>Aeto. Trousers</legs>
        <feet>Xaddi Boots</feet>
        <legs>Xaddi Cuisses</legs>
        <ammo>White Tathlum</ammo>
        <main>Twilight Scythe</main>
        <back>Toro Cape</back>
        <main>Kbiroj</main>
        <head>Twilight Helm</head>
        <body>Mekira Meikogai</body>
        <neck>Stoicheion Medal</neck>
        <left_ear>Merman's Earring</left_ear>
        <body>Miki. Breastplate</body>
        <item>Hi-Reraiser</item>
        <item>Pearlsack</item>
        <item>Instant Reraise</item>
        <legs>Gor. Brayettes +1</legs>
        <item>Pterygotus</item>
        <feet>Phorcys Schuhs</feet>
        <waist>Phasmida Belt</waist>
        <left_ear>Dudgeon Earring</left_ear>
        <body>Phorcys Korazin</body>
        <sub>Pole Grip</sub>
        <item>Gil</item>
      </set>
    </group>
  </sets>
</spellcast>